bpystubgen/__init__.py
bpystubgen/__main__.py
bpystubgen/directives.py
bpystubgen/nodes.py
bpystubgen/parser.py
bpystubgen/tasks.py
bpystubgen/writer.py
bpystubgen/patches/__init__.py
bpystubgen/patches/bgl.rst
bpystubgen/patches/blacklist.txt
bpystubgen/patches/bpy.rst
bpystubgen/patches/mathutils.Euler.rst
bpystubgen/patches/mathutils.Matrix.rst
bpystubgen/patches/mathutils.Quaternion.rst
bpystubgen/patches/mathutils.Vector.rst
bpystubgen-0.2.7.dist-info/LICENSE
bpystubgen-0.2.7.dist-info/METADATA
bpystubgen-0.2.7.dist-info/WHEEL
bpystubgen-0.2.7.dist-info/top_level.txt
bpystubgen-0.2.7.dist-info/RECORD
