Metadata-Version: 2.1
Name: bpystubgen
Version: 0.2.7
Summary: A utility to generate Python API stubs from documentation files in reStructuredText format.
Home-page: https://github.com/mysticfall/bpystubgen
Author: Xavier Cho
Author-email: mysticfallband@gmail.com
License: UNKNOWN
Platform: UNKNOWN
Classifier: Programming Language :: Python :: 3
Classifier: License :: OSI Approved :: GNU General Public License v3 or later (GPLv3+)
Classifier: Operating System :: OS Independent
License-File: LICENSE
Requires-Dist: docutils (==0.17.1)
Requires-Dist: sphinxcontrib-restbuilder (==0.3)
